vsutillib/pyqt/__init__.py
vsutillib/pyqt/messagebox.py
vsutillib/pyqt/qtUtils.py
vsutillib/pyqt/classes/QActionWidget.py
vsutillib/pyqt/classes/QComboLineEdit.py
vsutillib/pyqt/classes/QDarkPalette.py
vsutillib/pyqt/classes/QFileListWidget.py
vsutillib/pyqt/classes/QFormatLabel.py
vsutillib/pyqt/classes/QGenericThreads.py
vsutillib/pyqt/classes/QGroupSignal.py
vsutillib/pyqt/classes/QLineFrame.py
vsutillib/pyqt/classes/QMenuWidget.py
vsutillib/pyqt/classes/QOutputTextWidget.py
vsutillib/pyqt/classes/QProgressBar.py
vsutillib/pyqt/classes/QProgressIndicator.py
vsutillib/pyqt/classes/QPushButtonWidget.py
vsutillib/pyqt/classes/QRunInThread.py
vsutillib/pyqt/classes/QSignalLogHandler.py
vsutillib/pyqt/classes/QSystemTrayIconWidget.py
vsutillib/pyqt/classes/QWorker.py
vsutillib/pyqt/classes/SvgColor.py
vsutillib/pyqt/classes/TabWidget.py
vsutillib/pyqt/classes/TabWidgetExtension.py
vsutillib/pyqt/classes/__init__.py
vsutillib/pyqt/classes/insertTextHelpers.py
vsutillib_pyqt-1.6.2.dist-info/AUTHORS
vsutillib_pyqt-1.6.2.dist-info/LICENSE.txt
vsutillib_pyqt-1.6.2.dist-info/METADATA
vsutillib_pyqt-1.6.2.dist-info/WHEEL
vsutillib_pyqt-1.6.2.dist-info/top_level.txt
vsutillib_pyqt-1.6.2.dist-info/RECORD
