Metadata-Version: 2.1
Name: vsutillib-pyqt
Version: 1.6.2
Summary: vsutillib.pyqt sub package part of vsutillib
Home-page: https://pypi.org/project/vsutillib-pyqt/
Author: Efrain Vergara
Author-email: akai10tsuki@gmail.com
License: MIT
Platform: UNKNOWN
Requires-Python: >=3.8.1, <3.9
Requires-Dist: PySide2 (>=5.14)
Requires-Dist: vsutillib-macos (>=1.6.0)
